CHANGES.txt
README.txt
bootstrap.py
buildout.cfg
setup.py
src/zc/__init__.py
src/zc.selenium.egg-info/PKG-INFO
src/zc.selenium.egg-info/SOURCES.txt
src/zc.selenium.egg-info/dependency_links.txt
src/zc.selenium.egg-info/namespace_packages.txt
src/zc.selenium.egg-info/not-zip-safe
src/zc.selenium.egg-info/requires.txt
src/zc.selenium.egg-info/top_level.txt
src/zc/selenium/__init__.py
src/zc/selenium/configure.zcml
src/zc/selenium/dbs.py
src/zc/selenium/htmltest.py
src/zc/selenium/meta.zcml
src/zc/selenium/pytest.py
src/zc/selenium/pytest.txt
src/zc/selenium/resource.py
src/zc/selenium/results.pt
src/zc/selenium/results.py
src/zc/selenium/selenium.py
src/zc/selenium/selenium.txt
src/zc/selenium/tests.py
src/zc/selenium/tests.zcml
src/zc/selenium/zcml.py
src/zc/selenium/resources/Blank.html
src/zc/selenium/resources/InjectedRemoteRunner.html
src/zc/selenium/resources/RemoteRunner.html
src/zc/selenium/resources/SeleniumLog.html
src/zc/selenium/resources/TestPrompt.html
src/zc/selenium/resources/TestRunner-splash.html
src/zc/selenium/resources/TestRunner.hta
src/zc/selenium/resources/TestRunner.html
src/zc/selenium/resources/iedoc-core.xml
src/zc/selenium/resources/iedoc.xml
src/zc/selenium/resources/selenium-logo.png
src/zc/selenium/resources/selenium-test.css
src/zc/selenium/resources/selenium.css
src/zc/selenium/resources/domviewer/butmin.gif
src/zc/selenium/resources/domviewer/butplus.gif
src/zc/selenium/resources/domviewer/domviewer.css
src/zc/selenium/resources/domviewer/domviewer.html
src/zc/selenium/resources/domviewer/selenium-domviewer.js
src/zc/selenium/resources/icons/all.png
src/zc/selenium/resources/icons/continue.png
src/zc/selenium/resources/icons/continue_disabled.png
src/zc/selenium/resources/icons/pause.png
src/zc/selenium/resources/icons/pause_disabled.png
src/zc/selenium/resources/icons/selected.png
src/zc/selenium/resources/icons/step.png
src/zc/selenium/resources/icons/step_disabled.png
src/zc/selenium/resources/lib/prototype.js
src/zc/selenium/resources/lib/cssQuery/cssQuery-p.js
src/zc/selenium/resources/lib/cssQuery/src/cssQuery-level2.js
src/zc/selenium/resources/lib/cssQuery/src/cssQuery-level3.js
src/zc/selenium/resources/lib/cssQuery/src/cssQuery-standard.js
src/zc/selenium/resources/lib/cssQuery/src/cssQuery.js
