Metadata-Version: 1.0
Name: zc.selenium
Version: 1.2.1
Summary: Selenium integration for Zope 3
Home-page: http://svn.zope.org/zc.seleinum
Author: Zope Corporation
Author-email: info@zope.com
License: ZPL 2.1
Platform: UNKNOWN
